backtester_poo_272_mcd/__init__.py
backtester_poo_272_mcd/backtester.py
backtester_poo_272_mcd/data/cac40.json
backtester_poo_272_mcd/data/crypto_data.json
backtester_poo_272_mcd/data/eurostoxx50.json
backtester_poo_272_mcd/data/nikkei.json
backtester_poo_272_mcd/data/sp500.json
backtester_poo_272_mcd/data/univers_actions.json
backtester_poo_272_mcd/data/univers_actions.xlsx
backtester_poo_272_mcd/data_input.py
backtester_poo_272_mcd/data_inputs/__init__.py
backtester_poo_272_mcd/data_inputs/abstract_source.py
backtester_poo_272_mcd/data_inputs/binance_api.py
backtester_poo_272_mcd/data_inputs/custom_input.py
backtester_poo_272_mcd/data_inputs/df_input.py
backtester_poo_272_mcd/data_inputs/yahoo_api.py
backtester_poo_272_mcd/exceptions.py
backtester_poo_272_mcd/results.py
backtester_poo_272_mcd/strategies/__init__.py
backtester_poo_272_mcd/strategies/abstract_strategy.py
backtester_poo_272_mcd/strategies/exotic_strategies.py
backtester_poo_272_mcd/strategies/optimization_strategies.py
backtester_poo_272_mcd/strategies/risk_premia_strategies.py
backtester_poo_272_mcd/strategies/simple_strategies.py
backtester_poo_272_mcd/tools/__init__.py
backtester_poo_272_mcd/tools/enums.py
backtester_poo_272_mcd/tools/timer.py
backtester_poo_272_mcd-0.1.1.dist-info/entry_points.txt
backtester_poo_272_mcd-0.1.1.dist-info/LICENSE
backtester_poo_272_mcd-0.1.1.dist-info/METADATA
backtester_poo_272_mcd-0.1.1.dist-info/WHEEL
backtester_poo_272_mcd-0.1.1.dist-info/RECORD
