Metadata-Version: 2.1
Name: backtester_poo_272_mcd
Version: 0.1.1
Summary: POO Project for backtesting investment strategies
Home-page: https://github.com/baptistedfr/Backtesting-Investment-Strategies
License: MIT
Keywords: backtest,finance,trading,investment,strategies
Author: Baptiste DUFOUR
Author-email: bapdufo@gmail.com
Requires-Python: >=3.12
Classifier: License :: OSI Approved :: MIT License
Classifier: Programming Language :: Python :: 3
Classifier: Programming Language :: Python :: 3.12
Classifier: Programming Language :: Python :: 3.13
Requires-Dist: binance (>=0.3,<0.4)
Requires-Dist: ipykernel (>=6.29.5,<7.0.0)
Requires-Dist: matplotlib (>=3.9.2,<4.0.0)
Requires-Dist: nbformat (>=5.10.4)
Requires-Dist: numpy (>=2.2.1,<3.0.0)
Requires-Dist: openpyxl (>=3.1.5,<4.0.0)
Requires-Dist: plotly (>=5.24.1,<6.0.0)
Requires-Dist: pycoingecko (>=3.1.0,<4.0.0)
Requires-Dist: python-binance (>=1.0.21,<2.0.0)
Requires-Dist: scipy (>=1.14.1,<2.0.0)
Requires-Dist: yahoo-fin (>=0.8.9.1,<0.9.0.0)
Requires-Dist: yfinance (>=0.2.46,<0.3.0)
Project-URL: Repository, https://github.com/baptistedfr/Backtesting-Investment-Strategies
